.editorconfig
.gitignore
LICENSE
MANIFEST.in
README.md
mkdocs.yml
requirements.txt
requirements_dev.txt
requirements_docs.txt
setup.cfg
setup.py
.github/ISSUE_TEMPLATE/bug_report.md
.github/ISSUE_TEMPLATE/config.yml
.github/ISSUE_TEMPLATE/feature_request.md
.github/workflows/docs-build.yml
.github/workflows/docs.yml
.github/workflows/macos.yml
.github/workflows/pypi.yml
.github/workflows/ubuntu.yml
.github/workflows/windows.yml
bm_utilities/Address_finder.py
bm_utilities/__init__.py
bm_utilities/bm_utilities.py
bm_utilities/common.py
bm_utilities/quality_gates.py
bm_utilities.egg-info/PKG-INFO
bm_utilities.egg-info/SOURCES.txt
bm_utilities.egg-info/dependency_links.txt
bm_utilities.egg-info/not-zip-safe
bm_utilities.egg-info/requires.txt
bm_utilities.egg-info/top_level.txt
docs/bm_utilities.md
docs/changelog.md
docs/common.md
docs/contributing.md
docs/faq.md
docs/index.md
docs/installation.md
docs/usage.md
docs/examples/intro.ipynb
docs/overrides/main.html
tests/__init__.py
tests/test_bm_utilities.py