Metadata-Version: 2.1
Name: bm-utilities
Version: 0.1.4
Summary: A Python package for bm utilities
Home-page: https://github.com/Youssefamroo/bm_utilities
Author: youssef amr
Author-email: usef.amr11@gmail.com
License: MIT license
Keywords: bm_utilities
Classifier: Intended Audience :: Developers
Classifier: License :: OSI Approved :: MIT License
Classifier: Natural Language :: English
Classifier: Programming Language :: Python :: 3
Classifier: Programming Language :: Python :: 3.8
Classifier: Programming Language :: Python :: 3.9
Classifier: Programming Language :: Python :: 3.10
Classifier: Programming Language :: Python :: 3.11
Requires-Python: >=3.8
License-File: LICENSE
